rule/__init__.py
rule/abstract.py
rule/generic.py
rule/github.py
rule/manifold/__init__.py
rule/manifold/other.py
rule/manifold/this.py
rule/manifold/user.py
test/__init__.py
test/test_application.py
test/test_market.py
test/test_rule.py
test/test_util.py
test/examples/__init__.py
test/examples/test_amplified_odds.py
test/fixtures/cassettes/examples/amplified_odds/KlooTljBuurIgQddBI9D.yaml
test/fixtures/cassettes/examples/amplified_odds/fetch/amplified-odds-100x-will-a-nuclear-4acd2868830b.yaml
test/fixtures/cassettes/rule/github/test_ResolveToPR/LivInTheLookingGlass/ManifoldMarketManager/pr_14.yaml
test/fixtures/cassettes/rule/github/test_ResolveToPR/LivInTheLookingGlass/ManifoldMarketManager/pr_15.yaml
test/fixtures/cassettes/rule/github/test_ResolveToPR/LivInTheLookingGlass/ManifoldMarketManager/pr_2.yaml
test/fixtures/cassettes/rule/github/test_ResolveToPR/LivInTheLookingGlass/ManifoldMarketManager/pr_3.yaml
test/fixtures/cassettes/rule/github/test_ResolveToPR/LivInTheLookingGlass/ManifoldMarketManager/pr_4.yaml
test/fixtures/cassettes/rule/github/test_ResolveToPR/bcongdon/PyManifold/pr_1.yaml
test/fixtures/cassettes/rule/github/test_ResolveToPR/bcongdon/PyManifold/pr_2.yaml
test/fixtures/cassettes/rule/github/test_ResolveToPR/bcongdon/PyManifold/pr_3.yaml
test/fixtures/cassettes/rule/github/test_ResolveToPRDelta/LivInTheLookingGlass/ManifoldMarketManager/pr_14.yaml
test/fixtures/cassettes/rule/github/test_ResolveToPRDelta/LivInTheLookingGlass/ManifoldMarketManager/pr_15.yaml
test/fixtures/cassettes/rule/github/test_ResolveToPRDelta/LivInTheLookingGlass/ManifoldMarketManager/pr_2.yaml
test/fixtures/cassettes/rule/github/test_ResolveToPRDelta/LivInTheLookingGlass/ManifoldMarketManager/pr_3.yaml
test/fixtures/cassettes/rule/github/test_ResolveToPRDelta/LivInTheLookingGlass/ManifoldMarketManager/pr_4.yaml
test/fixtures/cassettes/rule/github/test_ResolveToPRDelta/bcongdon/PyManifold/pr_1.yaml
ManifoldMarketManager-0.7.0.1.dist-info/LICENSE
ManifoldMarketManager-0.7.0.1.dist-info/METADATA
ManifoldMarketManager-0.7.0.1.dist-info/WHEEL
ManifoldMarketManager-0.7.0.1.dist-info/top_level.txt
ManifoldMarketManager-0.7.0.1.dist-info/RECORD
