Metadata-Version: 2.1
Name: ManifoldMarketManager
Version: 0.7.0.1
Summary: Tools and market management for manifold.markets
Home-page: https://github.com/gappleto97/ManifoldMarketManager
Author: Olivia Appleton
Author-email: Liv@OliviaAppleton.com
License: AGPLv3
Classifier: Development Status :: 3 - Alpha
Classifier: Environment :: Console
Classifier: Intended Audience :: Developers
Classifier: Intended Audience :: Financial and Insurance Industry
Classifier: Intended Audience :: Science/Research
Classifier: License :: OSI Approved :: GNU Affero General Public License v3
Classifier: Programming Language :: Python
Classifier: Programming Language :: Python :: 3
Classifier: Programming Language :: Python :: 3 :: Only
Classifier: Programming Language :: Python :: 3.8
Classifier: Programming Language :: Python :: 3.9
Classifier: Programming Language :: Python :: 3.10
Classifier: Programming Language :: Python :: 3.11
Classifier: Programming Language :: Python :: Implementation :: CPython
Classifier: Programming Language :: Python :: Implementation :: PyPy
Classifier: Topic :: Internet
Classifier: Topic :: Other/Nonlisted Topic
Classifier: Typing :: Typed
Requires-Python: >=3.8
License-File: LICENSE
Requires-Dist: attrs
Requires-Dist: numpy (>=1.23.1)
Requires-Dist: requests (>=2.28.0)
Requires-Dist: requests-cache
Provides-Extra: all
Requires-Dist: ManifoldMarketManager[github,telegram,tests] ; extra == 'all'
Provides-Extra: github
Requires-Dist: github3.py ; extra == 'github'
Provides-Extra: telegram
Requires-Dist: python-telegram-bot (>=20.0a4) ; extra == 'telegram'
Provides-Extra: tests
Requires-Dist: flake8 (<5) ; extra == 'tests'
Requires-Dist: markdown (>=3.3) ; extra == 'tests'
Requires-Dist: pytest ; extra == 'tests'
Requires-Dist: pytest-benchmark ; extra == 'tests'
Requires-Dist: pytest-cov ; extra == 'tests'
Requires-Dist: pytest-flake8 ; extra == 'tests'
Requires-Dist: pytest-isort ; extra == 'tests'
Requires-Dist: pytest-mypy ; extra == 'tests'
Requires-Dist: pytest-regressions ; extra == 'tests'
Requires-Dist: pytest-xdist ; extra == 'tests'
Requires-Dist: vcrpy (>=4.1.1) ; extra == 'tests'
Requires-Dist: brotlipy ; extra == 'tests'
